apistar_request_id.py
apistar_request_id-0.2.1.dist-info/METADATA
apistar_request_id-0.2.1.dist-info/RECORD
apistar_request_id-0.2.1.dist-info/WHEEL
apistar_request_id-0.2.1.dist-info/top_level.txt
