Metadata-Version: 2.1
Name: apistar-request-id
Version: 0.2.1
Summary: Request id generation and propagation for API Star.
Home-page: UNKNOWN
License: UNKNOWN
Platform: UNKNOWN
Requires-Python: >=3.5
Requires-Dist: apistar (>=0.5)
